setup.py
stashward/__init__.py
stashward/formatter.py
stashward/handler.py
stashward.egg-info/PKG-INFO
stashward.egg-info/SOURCES.txt
stashward.egg-info/dependency_links.txt
stashward.egg-info/not-zip-safe
stashward.egg-info/requires.txt
stashward.egg-info/top_level.txt