Metadata-Version: 1.0
Name: stashward
Version: 0.1.4
Summary: A log formatter and handler for Python that implements the (poorly specified) logstash-forwarder protocol.
Home-page: UNKNOWN
Author: Matt Johnson
Author-email: mdj2@pdx.edu
License: UNKNOWN
Platform: UNKNOWN
Classifier: Programming Language :: Python :: 3
Classifier: Programming Language :: Python :: 2.6
